bacGWAStatLearn/ClassIndexing.py
bacGWAStatLearn/Snakefile
bacGWAStatLearn/__init__.py
bacGWAStatLearn/main.py
bacGWAStatLearn/FeatureSelect/ClassFeatureSelection.py
bacGWAStatLearn/FeatureSelect/__init__.py
bacGWAStatLearn/TreeTune/ClassParamAnalysis.py
bacGWAStatLearn/TreeTune/ClassTuning.py
bacGWAStatLearn/TreeTune/__init__.py
bacGWAStatLearn/scripts/GWAS_PreFilter_script0.py
bacGWAStatLearn/scripts/GWAS_Ranking_script4.py
bacGWAStatLearn/scripts/GWAS_ReTuning_script3.py
bacGWAStatLearn/scripts/GWAS_Selection_script2.py
bacGWAStatLearn/scripts/GWAS_Tuning_script1.py
bacGWAStatLearn/scripts/__init__.py
bacGWAStatLearn-0.1.3.dist-info/LICENSE
bacGWAStatLearn-0.1.3.dist-info/METADATA
bacGWAStatLearn-0.1.3.dist-info/WHEEL
bacGWAStatLearn-0.1.3.dist-info/entry_points.txt
bacGWAStatLearn-0.1.3.dist-info/top_level.txt
bacGWAStatLearn-0.1.3.dist-info/RECORD
