Metadata-Version: 2.1
Name: bacGWAStatLearn
Version: 0.1.3
Summary: A machine learning approach for conducting genome wide association studies (GWAS) on bacteria
Home-page: https://github.com/PaulDanPhillips/bacGWAStatLearn
Author: Paul Phillips
License: MIT
License-File: LICENSE
Requires-Dist: pandas
Requires-Dist: scipy
Requires-Dist: statsmodels
Requires-Dist: numpy ==1.23.5
Requires-Dist: scikit-learn
Requires-Dist: xgboost
Requires-Dist: matplotlib
Requires-Dist: joblib
Requires-Dist: snakemake
Requires-Dist: Boruta
Requires-Dist: shap
Requires-Dist: seaborn
Requires-Dist: plotnine
